{
  "name": "Cloudeye",
  "id": "cloudeye-grafana-datasource",
  "type": "datasource",

  "partials": {
    "config": "public/app/plugins/datasource/cloudeye/partials/config.html"
  },

  "metrics": true,
  "annotations": true,

  "info": {
    "description": "cloudeye json datasource",
    "author": {
      "name": "Huaweicloud groups",
      "url": "https://huaweicloud.com"
    },
    "logos": {
      "small": "img/cloudeye_logo.png",
      "large": "img/cloudeye_logo.png"
    },
    "links": [
      {"name": "GitHub", "url": "https://github.com/grafana/cloudeye-grafana"},
      {"name": "MIT License", "url": "https://github.com/huaweicloud/cloudeye-grafana/blob/master/LICENSE"}
    ],
    "version": "0.0.1",
    "updated": "2019-11-01"
  },

  "dependencies": {
    "grafanaVersion": "3.x.x",
    "plugins": [ ]
  },

  "metrics": true,
  "annotations": false
}
